LICENSE.txt
MANIFEST.in
README.rst
setup.py
django_pure_pagination.egg-info/PKG-INFO
django_pure_pagination.egg-info/SOURCES.txt
django_pure_pagination.egg-info/dependency_links.txt
django_pure_pagination.egg-info/not-zip-safe
django_pure_pagination.egg-info/top_level.txt
pure_pagination/__init__.py
pure_pagination/mixins.py
pure_pagination/models.py
pure_pagination/paginator.py
pure_pagination/tests.py
pure_pagination/templates/pure_pagination/pagination.html