Metadata-Version: 1.0
Name: django-pure-pagination
Version: 0.2.1
Summary: UNKNOWN
Home-page: https://github.com/jamespacileo/django-pure-pagination/
Author: James Pacileo
Author-email: jamespacileo@gmail.com
License: BSD
Keywords: pagination,django
Platform: UNKNOWN
Classifier: Programming Language :: Python
Classifier: Topic :: Software Development :: Libraries :: Python Modules
Classifier: Framework :: Django
Classifier: Environment :: Web Environment
